cancan/__init__.py
cancan/ability.py
cancan/access_rules.py
cancan/apps.py
cancan/context_processors.py
cancan/middleware.py
cancan/migrations/__init__.py
cancan/templatetags/__init__.py
cancan/templatetags/cancan_tags.py
cancan/testapp/__init__.py
cancan/testapp/abilities.py
cancan/testapp/models.py
cancan/testapp/testsettings.py
cancan/testapp/views.py
cancan/testapp/migrations/0001_initial.py
cancan/testapp/migrations/__init__.py
cancan/testapp/tests/__init__.py
cancan/testapp/tests/test_core.py
cancan/testapp/tests/test_middleware.py
cancan/testapp/tests/urls.py
example_project/__init__.py
example_project/abilities.py
example_project/asgi.py
example_project/manage.py
example_project/settings.py
example_project/urls.py
example_project/wsgi.py
example_project/sample/__init__.py
example_project/sample/admin.py
example_project/sample/apps.py
example_project/sample/models.py
example_project/sample/tests.py
example_project/sample/views.py
example_project/sample/migrations/0001_initial.py
example_project/sample/migrations/__init__.py
django_cancan-0.4.2.dist-info/LICENSE
django_cancan-0.4.2.dist-info/METADATA
django_cancan-0.4.2.dist-info/WHEEL
django_cancan-0.4.2.dist-info/top_level.txt
django_cancan-0.4.2.dist-info/RECORD
